openpipe/LICENSE
openpipe/__init__.py
openpipe/api_client/__init__.py
openpipe/api_client/client.py
openpipe/api_client/core/__init__.py
openpipe/api_client/core/api_error.py
openpipe/api_client/core/client_wrapper.py
openpipe/api_client/core/datetime_utils.py
openpipe/api_client/core/jsonable_encoder.py
openpipe/api_client/core/remove_none_from_dict.py
openpipe/api_client/environment.py
openpipe/api_client/types/__init__.py
openpipe/api_client/types/check_cache_response.py
openpipe/api_client/types/create_chat_completion_request_audio.py
openpipe/api_client/types/create_chat_completion_request_audio_format.py
openpipe/api_client/types/create_chat_completion_request_audio_voice.py
openpipe/api_client/types/create_chat_completion_request_function_call.py
openpipe/api_client/types/create_chat_completion_request_function_call_name.py
openpipe/api_client/types/create_chat_completion_request_functions_item.py
openpipe/api_client/types/create_chat_completion_request_messages_item.py
openpipe/api_client/types/create_chat_completion_request_messages_item_assistant.py
openpipe/api_client/types/create_chat_completion_request_messages_item_assistant_annotations_item.py
openpipe/api_client/types/create_chat_completion_request_messages_item_assistant_annotations_item_url_citation.py
openpipe/api_client/types/create_chat_completion_request_messages_item_assistant_audio.py
openpipe/api_client/types/create_chat_completion_request_messages_item_assistant_content.py
openpipe/api_client/types/create_chat_completion_request_messages_item_assistant_content_item.py
openpipe/api_client/types/create_chat_completion_request_messages_item_assistant_content_item_refusal.py
openpipe/api_client/types/create_chat_completion_request_messages_item_assistant_content_item_text.py
openpipe/api_client/types/create_chat_completion_request_messages_item_assistant_function_call.py
openpipe/api_client/types/create_chat_completion_request_messages_item_assistant_tool_calls_item.py
openpipe-5.0.0.dist-info/METADATA
openpipe-5.0.0.dist-info/WHEEL
openpipe-5.0.0.dist-info/RECORD
