Metadata-Version: 2.1
Name: openpipe
Version: 5.0.0
Summary: OpenPipe Python SDK: Fine-Tuning, Inference, and Metrics for Production Apps
Home-page: https://github.com/OpenPipe/OpenPipe
License: Apache-2.0
Author: Kyle Corbitt
Author-email: kyle@openpipe.ai
Requires-Python: >=3.8,<4.0
Classifier: License :: OSI Approved :: Apache Software License
Classifier: Programming Language :: Python :: 3
Classifier: Programming Language :: Python :: 3.8
Classifier: Programming Language :: Python :: 3.9
Classifier: Programming Language :: Python :: 3.10
Classifier: Programming Language :: Python :: 3.11
Classifier: Programming Language :: Python :: 3.12
Requires-Dist: anthropic (<=0.49.0)
Requires-Dist: attrs (>=23.2.0,<25.0.0)
Requires-Dist: httpx (>=0.27.0,<0.29.0)
Requires-Dist: openai (>=1.40,<=1.97.1)
Requires-Dist: python-dateutil (>=2.8.0,<3.0.0)
Project-URL: Repository, https://github.com/OpenPipe/OpenPipe
